README.rst
setup.py
jupyter_runner/__init__.py
jupyter_runner/cli.py
jupyter_runner/constant.py
jupyter_runner/execute.py
jupyter_runner/file_handler.py
jupyter_runner/mail.py
jupyter_runner.egg-info/PKG-INFO
jupyter_runner.egg-info/SOURCES.txt
jupyter_runner.egg-info/dependency_links.txt
jupyter_runner.egg-info/entry_points.txt
jupyter_runner.egg-info/requires.txt
jupyter_runner.egg-info/top_level.txt
tests/__init__.py
tests/test_execute.py
tests/test_mail.py