Metadata-Version: 1.1
Name: jupyter-runner
Version: 0.6.0
Summary: Jupyter notebook runner.
Home-page: UNKNOWN
Author: Omar Masmoudi
Author-email: UNKNOWN
License: UNKNOWN
Platform: UNKNOWN
Classifier: Programming Language :: Python :: 3.5
